erikrowens_de_toolkit/__init__.py
erikrowens_de_toolkit/main.py
erikrowens_de_toolkit/vm.py
erikrowens_de_toolkit-0.1.0.dist-info/METADATA
erikrowens_de_toolkit-0.1.0.dist-info/WHEEL
erikrowens_de_toolkit-0.1.0.dist-info/entry_points.txt
erikrowens_de_toolkit-0.1.0.dist-info/RECORD
